sem/__init__.py
sem/cli.py
sem/conditionalrunner.py
sem/database.py
sem/gridrunner.py
sem/lptrunner.py
sem/manager.py
sem/parallelrunner.py
sem/run_program.sh
sem/runner.py
sem/utils.py
sem-0.3.9.dist-info/LICENSE
sem-0.3.9.dist-info/METADATA
sem-0.3.9.dist-info/WHEEL
sem-0.3.9.dist-info/entry_points.txt
sem-0.3.9.dist-info/RECORD
