Metadata-Version: 2.1
Name: sem
Version: 0.3.9
Summary: A Simulation Execution Manager for ns-3
Home-page: https://github.com/signetlabdei/sem
License: GPL-2.0-only
Keywords: ns-3,simulation,execution
Author: Davide Magrin
Author-email: magrinda@dei.unipd.it
Requires-Python: >=3.9,<4
Classifier: License :: OSI Approved :: GNU General Public License v2 (GPLv2)
Classifier: Programming Language :: Python :: 3
Classifier: Programming Language :: Python :: 3.9
Classifier: Programming Language :: Python :: 3.10
Classifier: Programming Language :: Python :: 3.11
Classifier: Programming Language :: Python :: 3.12
Requires-Dist: click
Requires-Dist: drmaa
Requires-Dist: gitpython
Requires-Dist: numpy (>=1.26.0,<2.0.0)
Requires-Dist: pandas
Requires-Dist: salib (>=1.3.8,<2.0.0)
Requires-Dist: tinydb (>=4.0.0,<5.0.0)
Requires-Dist: tqdm
Requires-Dist: xarray
Project-URL: Repository, https://github.com/signetlabdei/sem
